[
    {
        "id": 1,
        "name": "chapel",
        "backgroundUrl": "./img/test.jpg",
        "textContent": [
            {
                "id": 1,
                "text": "Hello! Welcome"   
            },
            {
                "id": 2,
                "text": "sample message 1"   
            },
            {
                "id": 3,
                "text": "sample message 2"   
            },
            {
                "id": 4,
                "text": "Last message before going to next scene!"   
            }
        ]
    },
    {
        "id": 2,
        "name": "scene 2",
        "backgroundUrl": "./img/duke_1.jpg",
        "textContent": [
            {
                "id": 1,
                "text": "HHFDSKFJDKLFJYLKMFEWKLFMDSFMDSaf"   
            },
            {
                "id": 2,
                "text": "sample asdfasdfasdfmessage 1"   
            },
            {
                "id": 3,
                "text": "sample measdfasdfasdfasdssage 2"   
            },
            {
                "id": 4,
                "text": "Last mefsadfsadfasdfssage before going to next scene!"   
            }
        ]
    },
    {
        "id": 3,
        "name": "scene 3",
        "backgroundUrl": "./img/duke-chapel2.jpg",
        "textContent": [
            {
                "id": 1,
                "text": "Hello! Wedfsadfdsafslcome"   
            },
            {
                "id": 2,
                "text": "sampsadfasfdasdfasle message 1"   
            },
            {
                "id": 3,
                "text": "sampleasdfasdfasdf message 2"   
            },
            {
                "id": 4,
                "text": "Last message before going to next scasdfasdfasdfene!"   
            }
        ]
    }
]